{"assets/Ellipse 4.png":["assets/Ellipse 4.png"],"assets/Order Success.png":["assets/Order Success.png"],"assets/Order illustration.png":["assets/Order illustration.png"],"assets/Rectangle 387 (1).png":["assets/Rectangle 387 (1).png"],"assets/Rectangle 387.png":["assets/Rectangle 387.png"],"assets/Safe Food.png":["assets/Safe Food.png"],"assets/Tracking & Maps.png":["assets/Tracking & Maps.png"],"assets/ic_google.png":["assets/ic_google.png"],"assets/image 1.png":["assets/image 1.png"],"assets/image 3.png":["assets/image 3.png"],"assets/set-homemade-delicious-burgers-(2) 1.png":["assets/set-homemade-delicious-burgers-(2) 1.png"],"packages/cupertino_icons/assets/CupertinoIcons.ttf":["packages/cupertino_icons/assets/CupertinoIcons.ttf"]}